AzureK/AzureK.py
AzureK/__init__.py
AzureK-2.5.4.dist-info/LICENSE
AzureK-2.5.4.dist-info/METADATA
AzureK-2.5.4.dist-info/WHEEL
AzureK-2.5.4.dist-info/top_level.txt
AzureK-2.5.4.dist-info/RECORD
