Metadata-Version: 2.1
Name: AzureK
Version: 2.5.4
Summary: 科研用
Home-page: UNKNOWN
Author: flhsjjk
Author-email: flhsjjk@mail.ustc.edu.cn
License: UNKNOWN
Platform: UNKNOWN
Classifier: Programming Language :: Python :: 3.8
Classifier: License :: OSI Approved :: MIT License
Classifier: Operating System :: OS Independent
